odoo9_addon_partner_multi_image-9.0.1.0.0-py2.7-nspkg.pth
odoo9_addon_partner_multi_image-9.0.1.0.0.dist-info/DESCRIPTION.rst
odoo9_addon_partner_multi_image-9.0.1.0.0.dist-info/METADATA
odoo9_addon_partner_multi_image-9.0.1.0.0.dist-info/RECORD
odoo9_addon_partner_multi_image-9.0.1.0.0.dist-info/WHEEL
odoo9_addon_partner_multi_image-9.0.1.0.0.dist-info/metadata.json
odoo9_addon_partner_multi_image-9.0.1.0.0.dist-info/namespace_packages.txt
odoo9_addon_partner_multi_image-9.0.1.0.0.dist-info/top_level.txt
odoo_addons/partner_multi_image/README.rst
odoo_addons/partner_multi_image/__init__.py
odoo_addons/partner_multi_image/__openerp__.py
odoo_addons/partner_multi_image/hooks.py
odoo_addons/partner_multi_image/models/__init__.py
odoo_addons/partner_multi_image/models/res_partner.py
odoo_addons/partner_multi_image/static/description/icon.png
odoo_addons/partner_multi_image/tests/__init__.py
odoo_addons/partner_multi_image/tests/test_res_partner.py
odoo_addons/partner_multi_image/views/res_partner_view.xml
